src/hdl/FDTD/Bz.sv
module bz#(
    parameter FP_WIDTH = 16,    
    parameter FRAC_BITS = 13
)(
    input logic clk,
    input logic signed [FP_WIDTH - 1:0] C_B,
    input logic signed [FP_WIDTH - 1:0] bz_old,
    input logic signed [FP_WIDTH - 1:0] ey_left,
    input logic signed [FP_WIDTH - 1:0] ey_right,
    output logic signed [FP_WIDTH - 1:0] bz_new 
);

logic signed [FP_WIDTH - 1:0] bz_1_reg;
logic signed [FP_WIDTH:0] difference_reg; // one bit wider to prevent overflow
logic signed [2 * FP_WIDTH:0] bz_untruncated; // twice as long + 1 for overflow due to multiplication
logic signed [FP_WIDTH - 1 :0] bz_truncated; 


always_ff @(posedge clk) begin
    difference_reg <= ey_right - ey_left;
    bz_1_reg <= bz_old;
    bz_new <= bz_1_reg - bz_truncated;
end


    assign bz_untruncated = (C_B * difference_reg);
    assign bz_truncated = $signed(bz_untruncated[FRAC_BITS + FP_WIDTH - 1 : FRAC_BITS]);

endmodule

src/hdl/FDTD/Bz_tb.sv
`timescale 1ns/1ps

module bz_tb;
    parameter FP_WIDTH = 16;
    parameter FRAC_BITS = 13;

    logic clk;
    logic signed [FP_WIDTH-1:0] C_B;
    logic signed [FP_WIDTH-1:0] bz_old;
    logic signed [FP_WIDTH-1:0] ey_left;
    logic signed [FP_WIDTH-1:0] ey_right;
    logic signed [FP_WIDTH-1:0] bz_new;

    bz #(
        .FP_WIDTH(FP_WIDTH),
        .FRAC_BITS(FRAC_BITS)
    ) bz_test (
        .clk(clk),
        .C_B(C_B),
        .bz_old(bz_old),
        .ey_left(ey_left),
        .ey_right(ey_right),
        .bz_new(bz_new)
    );

    initial begin
        clk = 0;
        forever #5 clk = ~clk; 
    end

    initial begin
        $dumpfile("dump.vcd");
        $dumpvars(0, bz_tb);

        C_B = 16'sd2867; // 0.35 
        bz_old = 0;
        ey_left = 0;
        ey_right = 0;
        
        #40; 

        ey_left  = 16'sd8192; // 1.0 
        ey_right = 16'sd8192; // 1.0 
        bz_old   = 16'sd4096; // 0.5 
        
        #30;

        ey_left  = 16'sd4096; // 0.5
        ey_right = 16'sd8192; // 1.0
        
        #30; 
        // expect 2663 in dec

        $display("Simulation Complete. Open dump.vcd in GTKWave.");
        $finish;
    end
endmodule

src/hdl/FDTD/dump.vcd
$date
	Wed May 20 17:42:29 2026
$end
$version
	Icarus Verilog
$end
$timescale
	1ps
$end
$scope module bz_tb $end
$var wire 16 ! bz_new [15:0] $end
$var parameter 32 " FP_WIDTH $end
$var parameter 32 # FRAC_BITS $end
$var reg 16 $ C_B [15:0] $end
$var reg 16 % bz_old [15:0] $end
$var reg 1 & clk $end
$var reg 16 ' ey_left [15:0] $end
$var reg 16 ( ey_right [15:0] $end
$scope module bz_test $end
$var wire 16 ) C_B [15:0] $end
$var wire 16 * bz_old [15:0] $end
$var wire 1 & clk $end
$var wire 16 + ey_left [15:0] $end
$var wire 16 , ey_right [15:0] $end
$var wire 33 - bz_untruncated [32:0] $end
$var wire 16 . bz_truncated [15:0] $end
$var parameter 32 / FP_WIDTH $end
$var parameter 32 0 FRAC_BITS $end
$var reg 16 1 bz_1_reg [15:0] $end
$var reg 16 2 bz_new [15:0] $end
$var reg 17 3 difference_reg [16:0] $end
$upscope $end
$upscope $end
$enddefinitions $end
$comment Show the parameter values. $end
$dumpall
b1101 0
b10000 /
b1101 #
b10000 "
$end
#0
$dumpvars
bx 3
bx 2
bx 1
bx .
bx -
b0 ,
b0 +
b0 *
b101100110011 )
b0 (
b0 '
0&
b0 %
b101100110011 $
bx !
$end
#5000
b0 .
b0 1
b0 -
b0 3
1&
#10000
0&
#15000
b0 !
b0 2
1&
#20000
0&
#25000
1&
#30000
0&
#35000
1&
#40000
0&
b1000000000000 %
b1000000000000 *
b10000000000000 (
b10000000000000 ,
b10000000000000 '
b10000000000000 +
#45000
b1000000000000 1
1&
#50000
0&
#55000
b1000000000000 !
b1000000000000 2
1&
#60000
0&
#65000
1&
#70000
0&
b1000000000000 '
b1000000000000 +
#75000
b10110011001 .
b101100110011000000000000 -
b1000000000000 3
1&
#80000
0&
#85000
b101001100111 !
b101001100111 2
1&
